destination/__init__.py
destination/_version.py
destination/py.typed
destination-1.3.0.dist-info/LICENSE
destination-1.3.0.dist-info/WHEEL
destination-1.3.0.dist-info/METADATA
destination-1.3.0.dist-info/RECORD
