Metadata-Version: 2.1
Name: destination
Version: 1.3.0
Summary: A Regex Based Path Routing Library.
Home-page: https://github.com/futursolo/destination
License: MIT
Author: Kaede Hoshikawa
Author-email: futursolo@icloud.com
Requires-Python: >=3.6.1,<4.0.0
Classifier: License :: OSI Approved :: MIT License
Classifier: Operating System :: MacOS
Classifier: Operating System :: MacOS :: MacOS X
Classifier: Operating System :: Microsoft
Classifier: Operating System :: Microsoft :: Windows
Classifier: Operating System :: POSIX
Classifier: Operating System :: POSIX :: Linux
Classifier: Operating System :: Unix
Classifier: Programming Language :: Python
Classifier: Programming Language :: Python :: 3
Classifier: Programming Language :: Python :: 3 :: Only
Classifier: Programming Language :: Python :: 3.7
Classifier: Programming Language :: Python :: 3.8
Classifier: Programming Language :: Python :: 3.9
Classifier: Programming Language :: Python :: Implementation :: CPython
Requires-Dist: importlib-metadata (>=4.0.1,<5.0.0); python_version <= "3.7"
Project-URL: Repository, https://github.com/futursolo/destination
